offset_poly/__init__.py
offset_poly/offset.py
offset_poly/offset_corner.py
offset_poly/prepare_poly.py
offset_poly/py.typed
offset_poly-0.3.3.dist-info/METADATA
offset_poly-0.3.3.dist-info/WHEEL
offset_poly-0.3.3.dist-info/top_level.txt
offset_poly-0.3.3.dist-info/RECORD
