Metadata-Version: 2.1
Name: offset_poly
Version: 0.3.3
Summary: offset a polyline or polygon in 2d space
Author-email: Shay Hill <shay_public@hotmail.com>
License: MIT
Requires-Python: >=3.9
Requires-Dist: vec2-math
Provides-Extra: dev
Requires-Dist: commitizen ; extra == 'dev'
Requires-Dist: pre-commit ; extra == 'dev'
Requires-Dist: pytest ; extra == 'dev'
Requires-Dist: tox ; extra == 'dev'
